antisphinx.py
antiweb-0.9.1.data/scripts/antiweb.py
antiweb-0.9.1.dist-info/DESCRIPTION.rst
antiweb-0.9.1.dist-info/METADATA
antiweb-0.9.1.dist-info/RECORD
antiweb-0.9.1.dist-info/WHEEL
antiweb-0.9.1.dist-info/metadata.json
antiweb-0.9.1.dist-info/top_level.txt
antiweb-0.9.1.dist-info/zip-safe
antiweb_lib/__init__.py
antiweb_lib/directives.py
antiweb_lib/document.py
antiweb_lib/filechangehandler.py
antiweb_lib/write.py
antiweb_lib/readers/CReader.py
antiweb_lib/readers/CSharpReader.py
antiweb_lib/readers/ClojureReader.py
antiweb_lib/readers/GenericReader.py
antiweb_lib/readers/Line.py
antiweb_lib/readers/PythonReader.py
antiweb_lib/readers/Reader.py
antiweb_lib/readers/RstReader.py
antiweb_lib/readers/XmlReader.py
antiweb_lib/readers/__init__.py
antiweb_lib/readers/config.py
