Metadata-Version: 2.0
Name: antiweb
Version: 0.9.1
Summary: antiweb literate programming tool
Home-page: https://github.com/7enderhead/antiweb
Author: Michael Reithinger, Philipp Rathmanner, Lukas Tanner, Philipp Grandits, Christian Eitner
Author-email: antiweb@freelists.org
License: GPL
Download-URL: https://github.com/7enderhead/antiweb
Platform: any
Classifier: Development Status :: 4 - Beta
Classifier: Environment :: Console
Classifier: Environment :: Web Environment
Classifier: Intended Audience :: Developers
Classifier: License :: OSI Approved :: GNU General Public License (GPL)
Classifier: Operating System :: OS Independent
Classifier: Programming Language :: Python
Classifier: Topic :: Documentation
Classifier: Topic :: Utilities
Requires-Dist: Pygments (>=2.2.0)
Requires-Dist: Sphinx
Requires-Dist: babel
Requires-Dist: beautifulsoup4
Requires-Dist: watchdog
